webdriver_helper-2.4.1.dist-info/RECORD
webdriver_helper-2.4.1.dist-info/WHEEL
webdriver_helper-2.4.1.dist-info/METADATA
webdriver_helper/__init__.pyi
webdriver_helper/driver.cpython-311-darwin.so
webdriver_helper/upload_by_drop.js
webdriver_helper/driver.pyi
webdriver_helper/__init__.cpython-311-darwin.so
webdriver_helper/_driver.pyi
webdriver_helper/pom.cpython-311-darwin.so
webdriver_helper/pom.pyi
webdriver_helper/_driver.cpython-311-darwin.so
