Metadata-Version: 2.1
Name: webdriver-helper
Version: 2.4.1
Summary: 自动下载浏览器驱动，使selenium 4.0开箱即用，并一些提高增强的功能
License: Apache-2.0
Author-email: dongfangtianyu <7629022+dongfangtianyu@users.noreply.github.com>
Requires-Python: >=3.9
Requires-Dist: Appium-Python-Client==2.11.1
Requires-Dist: parse==1.19.0
Requires-Dist: selenium==4.11.2
Project-URL: Homepage, https://github.com/dongfangtianyu/webdriver-helper
